snmp_requests/__init__.py
snmp_requests/packet.py
snmp_requests/snmp_engine.py
snmp_requests/snmp_stuff.py
snmp_requests-0.0.8.dist-info/LICENSE.txt
snmp_requests-0.0.8.dist-info/METADATA
snmp_requests-0.0.8.dist-info/WHEEL
snmp_requests-0.0.8.dist-info/top_level.txt
snmp_requests-0.0.8.dist-info/RECORD
